datatransformationsbertas/__init__.py
datatransformationsbertas-0.8.0.dist-info/LICENSE
datatransformationsbertas-0.8.0.dist-info/METADATA
datatransformationsbertas-0.8.0.dist-info/WHEEL
datatransformationsbertas-0.8.0.dist-info/RECORD
