Metadata-Version: 2.1
Name: dataTransformationsBertas
Version: 0.8.0
Summary: Tool to automate data scientist daily work
License: MIT
Author: Bertoldas
Requires-Python: >=3.12,<4.0
Classifier: License :: OSI Approved :: MIT License
Classifier: Programming Language :: Python :: 3
Classifier: Programming Language :: Python :: 3.12
Requires-Dist: numpy (>=1.9.3,<2.0.0)
